Workbook

Sheet Dashboard
AB1: 0
B2: 📊 Project Tracker — Management Dashboard | AB2: =IF('Project Tracker'!D2="","",IF(COUNTIF('Project Tracker'!$D$2:D2,'Project Tracker'!D2)=1,MAX($AB$1:AB1)+1,"")) -> 1
B3: Live view of all projects — updates automatically as rows are added, edited, or removed in the Project Tracker sheet. | AB3: =IF('Project Tracker'!D3="","",IF(COUNTIF('Project Tracker'!$D$2:D3,'Project Tracker'!D3)=1,MAX($AB$1:AB2)+1,"")) -> 2
AB4: =IF('Project Tracker'!D4="","",IF(COUNTIF('Project Tracker'!$D$2:D4,'Project Tracker'!D4)=1,MAX($AB$1:AB3)+1,""))
AB5: =IF('Project Tracker'!D7="","",IF(COUNTIF('Project Tracker'!$D$2:D7,'Project Tracker'!D7)=1,MAX($AB$1:AB4)+1,""))
B6: 📁 TOTAL PROJECTS | E6: ✔ COMPLETED | H6: ⏳ IN PROGRESS | K6: ⏸ ON HOLD | N6: ○ NOT STARTED | AB6: =IF('Project Tracker'!D8="","",IF(COUNTIF('Project Tracker'!$D$2:D8,'Project Tracker'!D8)=1,MAX($AB$1:AB5)+1,""))
B7: =COUNTA(ProjectTracker[Client Name]) -> 339 | E7: =COUNTIF(ProjectTracker[Project Status],"Completed") -> 149 | H7: =COUNTIF(ProjectTracker[Project Status],"In Progress") -> 174 | K7: =COUNTIF(ProjectTracker[Project Status],"Hold") -> 7 | N7: =COUNTIF(ProjectTracker[Project Status],"Not Started") -> 9 | AB7: =IF('Project Tracker'!D9="","",IF(COUNTIF('Project Tracker'!$D$2:D9,'Project Tracker'!D9)=1,MAX($AB$1:AB6)+1,"")) -> 3
AB8: =IF('Project Tracker'!D10="","",IF(COUNTIF('Project Tracker'!$D$2:D10,'Project Tracker'!D10)=1,MAX($AB$1:AB7)+1,"")) -> 4
AB9: =IF('Project Tracker'!D11="","",IF(COUNTIF('Project Tracker'!$D$2:D11,'Project Tracker'!D11)=1,MAX($AB$1:AB8)+1,"")) -> 5
AB10: =IF('Project Tracker'!D12="","",IF(COUNTIF('Project Tracker'!$D$2:D12,'Project Tracker'!D12)=1,MAX($AB$1:AB9)+1,""))
B11: 📋 Auditor-wise Project Summary | AB11: =IF('Project Tracker'!D13="","",IF(COUNTIF('Project Tracker'!$D$2:D13,'Project Tracker'!D13)=1,MAX($AB$1:AB10)+1,""))
B12: The auditor list below is generated automatically from the Project Tracker sheet. Add, rename, or remove auditors there — this table (and the space reserved below it) updates on its own. | AB12: =IF('Project Tracker'!D14="","",IF(COUNTIF('Project Tracker'!$D$2:D14,'Project Tracker'!D14)=1,MAX($AB$1:AB11)+1,""))
AB13: =IF('Project Tracker'!D15="","",IF(COUNTIF('Project Tracker'!$D$2:D326,'Project Tracker'!D15)=1,MAX($AB$1:AB12)+1,""))
B14: 👤 Auditor | C14: ⚪ Not Started | D14: 🔵 In Progress | E14: 🟠 Hold | F14: 🟢 Completed | G14: Σ Total Projects | AB14: =IF('Project Tracker'!D16="","",IF(COUNTIF('Project Tracker'!$D$2:D16,'Project Tracker'!D16)=1,MAX($AB$1:AB13)+1,""))
B15: =IFERROR(INDEX('Project Tracker'!$D$2:$D$5040,MATCH(1,$AB$2:$AB$5000,0)),"") -> Dimple | C15: =IF($B15="","",COUNTIFS(ProjectTracker[Auditor],$B15,ProjectTracker[Project Status],"Not Started")) -> 0 | D15: =IF($B15="","",COUNTIFS(ProjectTracker[Auditor],$B15,ProjectTracker[Project Status],"In Progress")) -> 4 | E15: =IF($B15="","",COUNTIFS(ProjectTracker[Auditor],$B15,ProjectTracker[Project Status],"Hold")) -> 1 | F15: =IF($B15="","",COUNTIFS(ProjectTracker[Auditor],$B15,ProjectTracker[Project Status],"Completed")) -> 19 | G15: =IF($B15="","",SUM(C15:F15)) -> 24 | AB15: =IF('Project Tracker'!D17="","",IF(COUNTIF('Project Tracker'!$D$2:D17,'Project Tracker'!D17)=1,MAX($AB$1:AB14)+1,"")) -> 6
B16: =IFERROR(INDEX('Project Tracker'!$D$2:$D$5040,MATCH(2,$AB$2:$AB$5000,0)),"") -> Gautam Patidar | C16: =IF($B16="","",COUNTIFS(ProjectTracker[Auditor],$B16,ProjectTracker[Project Status],"Not Started")) -> 0 | D16: =IF($B16="","",COUNTIFS(ProjectTracker[Auditor],$B16,ProjectTracker[Project Status],"In Progress")) -> 6 | E16: =IF($B16="","",COUNTIFS(ProjectTracker[Auditor],$B16,ProjectTracker[Project Status],"Hold")) -> 0 | F16: =IF($B16="","",COUNTIFS(ProjectTracker[Auditor],$B16,ProjectTracker[Project Status],"Completed")) -> 2 | G16: =IF($B16="","",SUM(C16:F16)) -> 8 | AB16: =IF('Project Tracker'!D18="","",IF(COUNTIF('Project Tracker'!$D$2:D18,'Project Tracker'!D18)=1,MAX($AB$1:AB15)+1,""))
B17: =IFERROR(INDEX('Project Tracker'!$D$2:$D$5040,MATCH(3,$AB$2:$AB$5000,0)),"") -> Gautam Patidar | C17: =IF($B17="","",COUNTIFS(ProjectTracker[Auditor],$B17,ProjectTracker[Project Status],"Not Started")) -> 0 | D17: =IF($B17="","",COUNTIFS(ProjectTracker[Auditor],$B17,ProjectTracker[Project Status],"In Progress")) -> 6 | E17: =IF($B17="","",COUNTIFS(ProjectTracker[Auditor],$B17,ProjectTracker[Project Status],"Hold")) -> 0 | F17: =IF($B17="","",COUNTIFS(ProjectTracker[Auditor],$B17,ProjectTracker[Project Status],"Completed")) -> 2 | G17: =IF($B17="","",SUM(C17:F17)) -> 8 | AB17: =IF('Project Tracker'!D19="","",IF(COUNTIF('Project Tracker'!$D$2:D19,'Project Tracker'!D19)=1,MAX($AB$1:AB16)+1,""))
B18: =IFERROR(INDEX('Project Tracker'!$D$2:$D$5040,MATCH(4,$AB$2:$AB$5000,0)),"") -> Gautam Patidar | C18: =IF($B18="","",COUNTIFS(ProjectTracker[Auditor],$B18,ProjectTracker[Project Status],"Not Started")) -> 0 | D18: =IF($B18="","",COUNTIFS(ProjectTracker[Auditor],$B18,ProjectTracker[Project Status],"In Progress")) -> 6 | E18: =IF($B18="","",COUNTIFS(ProjectTracker[Auditor],$B18,ProjectTracker[Project Status],"Hold")) -> 0 | F18: =IF($B18="","",COUNTIFS(ProjectTracker[Auditor],$B18,ProjectTracker[Project Status],"Completed")) -> 2 | G18: =IF($B18="","",SUM(C18:F18)) -> 8 | AB18: =IF('Project Tracker'!D20="","",IF(COUNTIF('Project Tracker'!$D$2:D20,'Project Tracker'!D20)=1,MAX($AB$1:AB17)+1,"")) -> 7
B19: =IFERROR(INDEX('Project Tracker'!$D$2:$D$5040,MATCH(5,$AB$2:$AB$5000,0)),"") -> Akash | C19: =IF($B19="","",COUNTIFS(ProjectTracker[Auditor],$B19,ProjectTracker[Project Status],"Not Started")) -> 0 | D19: =IF($B19="","",COUNTIFS(ProjectTracker[Auditor],$B19,ProjectTracker[Project Status],"In Progress")) -> 12 | E19: =IF($B19="","",COUNTIFS(ProjectTracker[Auditor],$B19,ProjectTracker[Project Status],"Hold")) -> 0 | F19: =IF($B19="","",COUNTIFS(ProjectTracker[Auditor],$B19,ProjectTracker[Project Status],"Completed")) -> 4 | G19: =IF($B19="","",SUM(C19:F19)) -> 16 | AB19: =IF('Project Tracker'!D21="","",IF(COUNTIF('Project Tracker'!$D$2:D21,'Project Tracker'!D21)=1,MAX($AB$1:AB18)+1,""))
B20: =IFERROR(INDEX('Project Tracker'!$D$2:$D$5040,MATCH(6,$AB$2:$AB$5000,0)),"") -> Jayneel | C20: =IF($B20="","",COUNTIFS(ProjectTracker[Auditor],$B20,ProjectTracker[Project Status],"Not Started")) -> 0 | D20: =IF($B20="","",COUNTIFS(ProjectTracker[Auditor],$B20,ProjectTracker[Project Status],"In Progress")) -> 9 | E20: =IF($B20="","",COUNTIFS(ProjectTracker[Auditor],$B20,ProjectTracker[Project Status],"Hold")) -> 0 | F20: =IF($B20="","",COUNTIFS(ProjectTracker[Auditor],$B20,ProjectTracker[Project Status],"Completed")) -> 0 | G20: =IF($B20="","",SUM(C20:F20)) -> 9 | AB20: =IF('Project Tracker'!D22="","",IF(COUNTIF('Project Tracker'!$D$2:D22,'Project Tracker'!D22)=1,MAX($AB$1:AB19)+1,""))
B21: =IFERROR(INDEX('Project Tracker'!$D$2:$D$5040,MATCH(7,$AB$2:$AB$5000,0)),"") -> Anushree | C21: =IF($B21="","",COUNTIFS(ProjectTracker[Auditor],$B21,ProjectTracker[Project Status],"Not Started")) -> 0 | D21: =IF($B21="","",COUNTIFS(ProjectTracker[Auditor],$B21,ProjectTracker[Project Status],"In Progress")) -> 4 | E21: =IF($B21="","",COUNTIFS(ProjectTracker[Auditor],$B21,ProjectTracker[Project Status],"Hold")) -> 0 | F21: =IF($B21="","",COUNTIFS(ProjectTracker[Auditor],$B21,ProjectTracker[Project Status],"Completed")) -> 9 | G21: =IF($B21="","",SUM(C21:F21)) -> 13 | AB21: =IF('Project Tracker'!D23="","",IF(COUNTIF('Project Tracker'!$D$2:D23,'Project Tracker'!D23)=1,MAX($AB$1:AB20)+1,""))
B22: =IFERROR(INDEX('Project Tracker'!$D$2:$D$5040,MATCH(8,$AB$2:$AB$5000,0)),"") -> Pratham | C22: =IF($B22="","",COUNTIFS(ProjectTracker[Auditor],$B22,ProjectTracker[Project Status],"Not Started")) -> 0 | D22: =IF($B22="","",COUNTIFS(ProjectTracker[Auditor],$B22,ProjectTracker[Project Status],"In Progress")) -> 3 | E22: =IF($B22="","",COUNTIFS(ProjectTracker[Auditor],$B22,ProjectTracker[Project Status],"Hold")) -> 1 | F22: =IF($B22="","",COUNTIFS(ProjectTracker[Auditor],$B22,ProjectTracker[Project Status],"Completed")) -> 15 | G22: =IF($B22="","",SUM(C22:F22)) -> 19 | AB22: =IF('Project Tracker'!D24="","",IF(COUNTIF('Project Tracker'!$D$2:D24,'Project Tracker'!D24)=1,MAX($AB$1:AB21)+1,""))
B23: =IFERROR(INDEX('Project Tracker'!$D$2:$D$5040,MATCH(9,$AB$2:$AB$5000,0)),"") -> Gautam Patidar | C23: =IF($B23="","",COUNTIFS(ProjectTracker[Auditor],$B23,ProjectTracker[Project Status],"Not Started")) -> 0 | D23: =IF($B23="","",COUNTIFS(ProjectTracker[Auditor],$B23,ProjectTracker[Project Status],"In Progress")) -> 6 | E23: =IF($B23="","",COUNTIFS(ProjectTracker[Auditor],$B23,ProjectTracker[Project Status],"Hold")) -> 0 | F23: =IF($B23="","",COUNTIFS(ProjectTracker[Auditor],$B23,ProjectTracker[Project Status],"Completed")) -> 2 | G23: =IF($B23="","",SUM(C23:F23)) -> 8 | AB23: =IF('Project Tracker'!D25="","",IF(COUNTIF('Project Tracker'!$D$2:D25,'Project Tracker'!D25)=1,MAX($AB$1:AB22)+1,""))
B24: =IFERROR(INDEX('Project Tracker'!$D$2:$D$5040,MATCH(10,$AB$2:$AB$5000,0)),"") -> Dimple | C24: =IF($B24="","",COUNTIFS(ProjectTracker[Auditor],$B24,ProjectTracker[Project Status],"Not Started")) -> 0 | D24: =IF($B24="","",COUNTIFS(ProjectTracker[Auditor],$B24,ProjectTracker[Project Status],"In Progress")) -> 4 | E24: =IF($B24="","",COUNTIFS(ProjectTracker[Auditor],$B24,ProjectTracker[Project Status],"Hold")) -> 1 | F24: =IF($B24="","",COUNTIFS(ProjectTracker[Auditor],$B24,ProjectTracker[Project Status],"Completed")) -> 19 | G24: =IF($B24="","",SUM(C24:F24)) -> 24 | AB24: =IF('Project Tracker'!D26="","",IF(COUNTIF('Project Tracker'!$D$2:D26,'Project Tracker'!D26)=1,MAX($AB$1:AB23)+1,""))
B25: =IFERROR(INDEX('Project Tracker'!$D$2:$D$5040,MATCH(11,$AB$2:$AB$5000,0)),"") -> Jayraj | C25: =IF($B25="","",COUNTIFS(ProjectTracker[Auditor],$B25,ProjectTracker[Project Status],"Not Started")) -> 0 | D25: =IF($B25="","",COUNTIFS(ProjectTracker[Auditor],$B25,ProjectTracker[Project Status],"In Progress")) -> 3 | E25: =IF($B25="","",COUNTIFS(ProjectTracker[Auditor],$B25,ProjectTracker[Project Status],"Hold")) -> 0 | F25: =IF($B25="","",COUNTIFS(ProjectTracker[Auditor],$B25,ProjectTracker[Project Status],"Completed")) -> 1 | G25: =IF($B25="","",SUM(C25:F25)) -> 4 | AB25: =IF('Project Tracker'!D27="","",IF(COUNTIF('Project Tracker'!$D$2:D27,'Project Tracker'!D27)=1,MAX($AB$1:AB24)+1,"")) -> 8
B26: =IFERROR(INDEX('Project Tracker'!$D$2:$D$5040,MATCH(12,$AB$2:$AB$5000,0)),"") -> Jayneel Chokshi | C26: =IF($B26="","",COUNTIFS(ProjectTracker[Auditor],$B26,ProjectTracker[Project Status],"Not Started")) -> 0 | D26: =IF($B26="","",COUNTIFS(ProjectTracker[Auditor],$B26,ProjectTracker[Project Status],"In Progress")) -> 3 | E26: =IF($B26="","",COUNTIFS(ProjectTracker[Auditor],$B26,ProjectTracker[Project Status],"Hold")) -> 0 | F26: =IF($B26="","",COUNTIFS(ProjectTracker[Auditor],$B26,ProjectTracker[Project Status],"Completed")) -> 8 | G26: =IF($B26="","",SUM(C26:F26)) -> 11 | AB26: =IF('Project Tracker'!D28="","",IF(COUNTIF('Project Tracker'!$D$2:D28,'Project Tracker'!D28)=1,MAX($AB$1:AB25)+1,"")) -> 9
B27: =IFERROR(INDEX('Project Tracker'!$D$2:$D$5040,MATCH(13,$AB$2:$AB$5000,0)),"") -> Gautam Patidar , Anushree pillai, Aditya katkar | C27: =IF($B27="","",COUNTIFS(ProjectTracker[Auditor],$B27,ProjectTracker[Project Status],"Not Started")) -> 0 | D27: =IF($B27="","",COUNTIFS(ProjectTracker[Auditor],$B27,ProjectTracker[Project Status],"In Progress")) -> 0 | E27: =IF($B27="","",COUNTIFS(ProjectTracker[Auditor],$B27,ProjectTracker[Project Status],"Hold")) -> 0 | F27: =IF($B27="","",COUNTIFS(ProjectTracker[Auditor],$B27,ProjectTracker[Project Status],"Completed")) -> 3 | G27: =IF($B27="","",SUM(C27:F27)) -> 3 | AB27: =IF('Project Tracker'!D29="","",IF(COUNTIF('Project Tracker'!$D$2:D29,'Project Tracker'!D29)=1,MAX($AB$1:AB26)+1,""))
B28: =IFERROR(INDEX('Project Tracker'!$D$2:$D$5040,MATCH(14,$AB$2:$AB$5000,0)),"") -> Jayraj | C28: =IF($B28="","",COUNTIFS(ProjectTracker[Auditor],$B28,ProjectTracker[Project Status],"Not Started")) -> 0 | D28: =IF($B28="","",COUNTIFS(ProjectTracker[Auditor],$B28,ProjectTracker[Project Status],"In Progress")) -> 3 | E28: =IF($B28="","",COUNTIFS(ProjectTracker[Auditor],$B28,ProjectTracker[Project Status],"Hold")) -> 0 | F28: =IF($B28="","",COUNTIFS(ProjectTracker[Auditor],$B28,ProjectTracker[Project Status],"Completed")) -> 1 | G28: =IF($B28="","",SUM(C28:F28)) -> 4 | AB28: =IF('Project Tracker'!D30="","",IF(COUNTIF('Project Tracker'!$D$2:D30,'Project Tracker'!D30)=1,MAX($AB$1:AB27)+1,""))
B29: =IFERROR(INDEX('Project Tracker'!$D$2:$D$5040,MATCH(15,$AB$2:$AB$5000,0)),"") -> Jayraj, Anushree | C29: =IF($B29="","",COUNTIFS(ProjectTracker[Auditor],$B29,ProjectTracker[Project Status],"Not Started")) -> 0 | D29: =IF($B29="","",COUNTIFS(ProjectTracker[Auditor],$B29,ProjectTracker[Project Status],"In Progress")) -> 4 | E29: =IF($B29="","",COUNTIFS(ProjectTracker[Auditor],$B29,ProjectTracker[Project Status],"Hold")) -> 0 | F29: =IF($B29="","",COUNTIFS(ProjectTracker[Auditor],$B29,ProjectTracker[Project Status],"Completed")) -> 0 | G29: =IF($B29="","",SUM(C29:F29)) -> 4 | AB29: =IF('Project Tracker'!D31="","",IF(COUNTIF('Project Tracker'!$D$2:D31,'Project Tracker'!D31)=1,MAX($AB$1:AB28)+1,"")) -> 10
B30: =IFERROR(INDEX('Project Tracker'!$D$2:$D$5040,MATCH(16,$AB$2:$AB$5000,0)),"") -> Gautam Patidar | C30: =IF($B30="","",COUNTIFS(ProjectTracker[Auditor],$B30,ProjectTracker[Project Status],"Not Started")) -> 0 | D30: =IF($B30="","",COUNTIFS(ProjectTracker[Auditor],$B30,ProjectTracker[Project Status],"In Progress")) -> 6 | E30: =IF($B30="","",COUNTIFS(ProjectTracker[Auditor],$B30,ProjectTracker[Project Status],"Hold")) -> 0 | F30: =IF($B30="","",COUNTIFS(ProjectTracker[Auditor],$B30,ProjectTracker[Project Status],"Completed")) -> 2 | G30: =IF($B30="","",SUM(C30:F30)) -> 8 | AB30: =IF('Project Tracker'!D32="","",IF(COUNTIF('Project Tracker'!$D$2:D32,'Project Tracker'!D32)=1,MAX($AB$1:AB29)+1,""))
B31: =IFERROR(INDEX('Project Tracker'!$D$2:$D$5040,MATCH(17,$AB$2:$AB$5000,0)),"") -> Kavish | C31: =IF($B31="","",COUNTIFS(ProjectTracker[Auditor],$B31,ProjectTracker[Project Status],"Not Started")) -> 0 | D31: =IF($B31="","",COUNTIFS(ProjectTracker[Auditor],$B31,ProjectTracker[Project Status],"In Progress")) -> 0 | E31: =IF($B31="","",COUNTIFS(ProjectTracker[Auditor],$B31,ProjectTracker[Project Status],"Hold")) -> 0 | F31: =IF($B31="","",COUNTIFS(ProjectTracker[Auditor],$B31,ProjectTracker[Project Status],"Completed")) -> 1 | G31: =IF($B31="","",SUM(C31:F31)) -> 1 | AB31: =IF('Project Tracker'!D33="","",IF(COUNTIF('Project Tracker'!$D$2:D33,'Project Tracker'!D33)=1,MAX($AB$1:AB30)+1,"")) -> 11
B32: =IFERROR(INDEX('Project Tracker'!$D$2:$D$5040,MATCH(18,$AB$2:$AB$5000,0)),"") -> Alphae | C32: =IF($B32="","",COUNTIFS(ProjectTracker[Auditor],$B32,ProjectTracker[Project Status],"Not Started")) -> 1 | D32: =IF($B32="","",COUNTIFS(ProjectTracker[Auditor],$B32,ProjectTracker[Project Status],"In Progress")) -> 10 | E32: =IF($B32="","",COUNTIFS(ProjectTracker[Auditor],$B32,ProjectTracker[Project Status],"Hold")) -> 1 | F32: =IF($B32="","",COUNTIFS(ProjectTracker[Auditor],$B32,ProjectTracker[Project Status],"Completed")) -> 6 | G32: =IF($B32="","",SUM(C32:F32)) -> 18 | AB32: =IF('Project Tracker'!D34="","",IF(COUNTIF('Project Tracker'!$D$2:D34,'Project Tracker'!D34)=1,MAX($AB$1:AB31)+1,""))
B33: =IFERROR(INDEX('Project Tracker'!$D$2:$D$5040,MATCH(19,$AB$2:$AB$5000,0)),"") -> Ashutosh, Anushree | C33: =IF($B33="","",COUNTIFS(ProjectTracker[Auditor],$B33,ProjectTracker[Project Status],"Not Started")) -> 0 | D33: =IF($B33="","",COUNTIFS(ProjectTracker[Auditor],$B33,ProjectTracker[Project Status],"In Progress")) -> 0 | E33: =IF($B33="","",COUNTIFS(ProjectTracker[Auditor],$B33,ProjectTracker[Project Status],"Hold")) -> 0 | F33: =IF($B33="","",COUNTIFS(ProjectTracker[Auditor],$B33,ProjectTracker[Project Status],"Completed")) -> 1 | G33: =IF($B33="","",SUM(C33:F33)) -> 1 | AB33: =IF('Project Tracker'!D35="","",IF(COUNTIF('Project Tracker'!$D$2:D35,'Project Tracker'!D35)=1,MAX($AB$1:AB32)+1,""))
B34: =IFERROR(INDEX('Project Tracker'!$D$2:$D$5040,MATCH(20,$AB$2:$AB$5000,0)),"") -> Pratham | C34: =IF($B34="","",COUNTIFS(ProjectTracker[Auditor],$B34,ProjectTracker[Project Status],"Not Started")) -> 0 | D34: =IF($B34="","",COUNTIFS(ProjectTracker[Auditor],$B34,ProjectTracker[Project Status],"In Progress")) -> 3 | E34: =IF($B34="","",COUNTIFS(ProjectTracker[Auditor],$B34,ProjectTracker[Project Status],"Hold")) -> 1 | F34: =IF($B34="","",COUNTIFS(ProjectTracker[Auditor],$B34,ProjectTracker[Project Status],"Completed")) -> 15 | G34: =IF($B34="","",SUM(C34:F34)) -> 19 | AB34: =IF('Project Tracker'!D36="","",IF(COUNTIF('Project Tracker'!$D$2:D36,'Project Tracker'!D36)=1,MAX($AB$1:AB33)+1,"")) -> 12
B35: =IFERROR(INDEX('Project Tracker'!$D$2:$D$5040,MATCH(21,$AB$2:$AB$5000,0)),"") -> Sagar | C35: =IF($B35="","",COUNTIFS(ProjectTracker[Auditor],$B35,ProjectTracker[Project Status],"Not Started")) -> 0 | D35: =IF($B35="","",COUNTIFS(ProjectTracker[Auditor],$B35,ProjectTracker[Project Status],"In Progress")) -> 0 | E35: =IF($B35="","",COUNTIFS(ProjectTracker[Auditor],$B35,ProjectTracker[Project Status],"Hold")) -> 0 | F35: =IF($B35="","",COUNTIFS(ProjectTracker[Auditor],$B35,ProjectTracker[Project Status],"Completed")) -> 1 | G35: =IF($B35="","",SUM(C35:F35)) -> 1 | AB35: =IF('Project Tracker'!D37="","",IF(COUNTIF('Project Tracker'!$D$2:D37,'Project Tracker'!D37)=1,MAX($AB$1:AB34)+1,""))
B36: =IFERROR(INDEX('Project Tracker'!$D$2:$D$5040,MATCH(22,$AB$2:$AB$5000,0)),"") -> Anushree | C36: =IF($B36="","",COUNTIFS(ProjectTracker[Auditor],$B36,ProjectTracker[Project Status],"Not Started")) -> 0 | D36: =IF($B36="","",COUNTIFS(ProjectTracker[Auditor],$B36,ProjectTracker[Project Status],"In Progress")) -> 4 | E36: =IF($B36="","",COUNTIFS(ProjectTracker[Auditor],$B36,ProjectTracker[Project Status],"Hold")) -> 0 | F36: =IF($B36="","",COUNTIFS(ProjectTracker[Auditor],$B36,ProjectTracker[Project Status],"Completed")) -> 9 | G36: =IF($B36="","",SUM(C36:F36)) -> 13 | AB36: =IF('Project Tracker'!D38="","",IF(COUNTIF('Project Tracker'!$D$2:D38,'Project Tracker'!D38)=1,MAX($AB$1:AB35)+1,""))
B37: =IFERROR(INDEX('Project Tracker'!$D$2:$D$5040,MATCH(23,$AB$2:$AB$5000,0)),"") -> Alphae | C37: =IF($B37="","",COUNTIFS(ProjectTracker[Auditor],$B37,ProjectTracker[Project Status],"Not Started")) -> 1 | D37: =IF($B37="","",COUNTIFS(ProjectTracker[Auditor],$B37,ProjectTracker[Project Status],"In Progress")) -> 10 | E37: =IF($B37="","",COUNTIFS(ProjectTracker[Auditor],$B37,ProjectTracker[Project Status],"Hold")) -> 1 | F37: =IF($B37="","",COUNTIFS(ProjectTracker[Auditor],$B37,ProjectTracker[Project Status],"Completed")) -> 6 | G37: =IF($B37="","",SUM(C37:F37)) -> 18 | AB37: =IF('Project Tracker'!D39="","",IF(COUNTIF('Project Tracker'!$D$2:D39,'Project Tracker'!D39)=1,MAX($AB$1:AB36)+1,""))
B38: =IFERROR(INDEX('Project Tracker'!$D$2:$D$5040,MATCH(24,$AB$2:$AB$5000,0)),"") -> Vineet, Purvi | C38: =IF($B38="","",COUNTIFS(ProjectTracker[Auditor],$B38,ProjectTracker[Project Status],"Not Started")) -> 0 | D38: =IF($B38="","",COUNTIFS(ProjectTracker[Auditor],$B38,ProjectTracker[Project Status],"In Progress")) -> 0 | E38: =IF($B38="","",COUNTIFS(ProjectTracker[Auditor],$B38,ProjectTracker[Project Status],"Hold")) -> 0 | F38: =IF($B38="","",COUNTIFS(ProjectTracker[Auditor],$B38,ProjectTracker[Project Status],"Completed")) -> 1 | G38: =IF($B38="","",SUM(C38:F38)) -> 1 | AB38: =IF('Project Tracker'!D40="","",IF(COUNTIF('Project Tracker'!$D$2:D40,'Project Tracker'!D40)=1,MAX($AB$1:AB37)+1,"")) -> 13
B39: =IFERROR(INDEX('Project Tracker'!$D$2:$D$5040,MATCH(25,$AB$2:$AB$5000,0)),"") -> Pratham | C39: =IF($B39="","",COUNTIFS(ProjectTracker[Auditor],$B39,ProjectTracker[Project Status],"Not Started")) -> 0 | D39: =IF($B39="","",COUNTIFS(ProjectTracker[Auditor],$B39,ProjectTracker[Project Status],"In Progress")) -> 3 | E39: =IF($B39="","",COUNTIFS(ProjectTracker[Auditor],$B39,ProjectTracker[Project Status],"Hold")) -> 1 | F39: =IF($B39="","",COUNTIFS(ProjectTracker[Auditor],$B39,ProjectTracker[Project Status],"Completed")) -> 15 | G39: =IF($B39="","",SUM(C39:F39)) -> 19 | AB39: =IF('Project Tracker'!D41="","",IF(COUNTIF('Project Tracker'!$D$2:D41,'Project Tracker'!D41)=1,MAX($AB$1:AB38)+1,""))
B40: =IFERROR(INDEX('Project Tracker'!$D$2:$D$5040,MATCH(26,$AB$2:$AB$5000,0)),"") -> Akash | C40: =IF($B40="","",COUNTIFS(ProjectTracker[Auditor],$B40,ProjectTracker[Project Status],"Not Started")) -> 0 | D40: =IF($B40="","",COUNTIFS(ProjectTracker[Auditor],$B40,ProjectTracker[Project Status],"In Progress")) -> 12 | E40: =IF($B40="","",COUNTIFS(ProjectTracker[Auditor],$B40,ProjectTracker[Project Status],"Hold")) -> 0 | F40: =IF($B40="","",COUNTIFS(ProjectTracker[Auditor],$B40,ProjectTracker[Project Status],"Completed")) -> 4 | G40: =IF($B40="","",SUM(C40:F40)) -> 16 | AB40: =IF('Project Tracker'!D42="","",IF(COUNTIF('Project Tracker'!$D$2:D42,'Project Tracker'!D42)=1,MAX($AB$1:AB39)+1,""))
B41: =IFERROR(INDEX('Project Tracker'!$D$2:$D$5040,MATCH(27,$AB$2:$AB$5000,0)),"") -> Vineet | C41: =IF($B41="","",COUNTIFS(ProjectTracker[Auditor],$B41,ProjectTracker[Project Status],"Not Started")) -> 4 | D41: =IF($B41="","",COUNTIFS(ProjectTracker[Auditor],$B41,ProjectTracker[Project Status],"In Progress")) -> 4 | E41: =IF($B41="","",COUNTIFS(ProjectTracker[Auditor],$B41,ProjectTracker[Project Status],"Hold")) -> 1 | F41: =IF($B41="","",COUNTIFS(ProjectTracker[Auditor],$B41,ProjectTracker[Project Status],"Completed")) -> 10 | G41: =IF($B41="","",SUM(C41:F41)) -> 19 | AB41: =IF('Project Tracker'!D43="","",IF(COUNTIF('Project Tracker'!$D$2:D43,'Project Tracker'!D43)=1,MAX($AB$1:AB40)+1,""))
B42: =IFERROR(INDEX('Project Tracker'!$D$2:$D$5040,MATCH(28,$AB$2:$AB$5000,0)),"") -> Aditya | C42: =IF($B42="","",COUNTIFS(ProjectTracker[Auditor],$B42,ProjectTracker[Project Status],"Not Started")) -> 0 | D42: =IF($B42="","",COUNTIFS(ProjectTracker[Auditor],$B42,ProjectTracker[Project Status],"In Progress")) -> 5 | E42: =IF($B42="","",COUNTIFS(ProjectTracker[Auditor],$B42,ProjectTracker[Project Status],"Hold")) -> 0 | F42: =IF($B42="","",COUNTIFS(ProjectTracker[Auditor],$B42,ProjectTracker[Project Status],"Completed")) -> 2 | G42: =IF($B42="","",SUM(C42:F42)) -> 7 | AB42: =IF('Project Tracker'!D44="","",IF(COUNTIF('Project Tracker'!$D$2:D44,'Project Tracker'!D44)=1,MAX($AB$1:AB41)+1,""))
B43: =IFERROR(INDEX('Project Tracker'!$D$2:$D$5040,MATCH(29,$AB$2:$AB$5000,0)),"") -> Deven | C43: =IF($B43="","",COUNTIFS(ProjectTracker[Auditor],$B43,ProjectTracker[Project Status],"Not Started")) -> 0 | D43: =IF($B43="","",COUNTIFS(ProjectTracker[Auditor],$B43,ProjectTracker[Project Status],"In Progress")) -> 0 | E43: =IF($B43="","",COUNTIFS(ProjectTracker[Auditor],$B43,ProjectTracker[Project Status],"Hold")) -> 0 | F43: =IF($B43="","",COUNTIFS(ProjectTracker[Auditor],$B43,ProjectTracker[Project Status],"Completed")) -> 4 | G43: =IF($B43="","",SUM(C43:F43)) -> 4 | AB43: =IF('Project Tracker'!D45="","",IF(COUNTIF('Project Tracker'!$D$2:D45,'Project Tracker'!D45)=1,MAX($AB$1:AB42)+1,""))
B44: =IFERROR(INDEX('Project Tracker'!$D$2:$D$5040,MATCH(30,$AB$2:$AB$5000,0)),"") -> Vineet | C44: =IF($B44="","",COUNTIFS(ProjectTracker[Auditor],$B44,ProjectTracker[Project Status],"Not Started")) -> 4 | D44: =IF($B44="","",COUNTIFS(ProjectTracker[Auditor],$B44,ProjectTracker[Project Status],"In Progress")) -> 4 | E44: =IF($B44="","",COUNTIFS(ProjectTracker[Auditor],$B44,ProjectTracker[Project Status],"Hold")) -> 1 | F44: =IF($B44="","",COUNTIFS(ProjectTracker[Auditor],$B44,ProjectTracker[Project Status],"Completed")) -> 10 | G44: =IF($B44="","",SUM(C44:F44)) -> 19 | AB44: =IF('Project Tracker'!D46="","",IF(COUNTIF('Project Tracker'!$D$2:D46,'Project Tracker'!D46)=1,MAX($AB$1:AB43)+1,""))
B45: =IFERROR(INDEX('Project Tracker'!$D$2:$D$5040,MATCH(31,$AB$2:$AB$5000,0)),"") -> Gourav | C45: =IF($B45="","",COUNTIFS(ProjectTracker[Auditor],$B45,ProjectTracker[Project Status],"Not Started")) -> 0 | D45: =IF($B45="","",COUNTIFS(ProjectTracker[Auditor],$B45,ProjectTracker[Project Status],"In Progress")) -> 2 | E45: =IF($B45="","",COUNTIFS(ProjectTracker[Auditor],$B45,ProjectTracker[Project Status],"Hold")) -> 0 | F45: =IF($B45="","",COUNTIFS(ProjectTracker[Auditor],$B45,ProjectTracker[Project Status],"Completed")) -> 8 | G45: =IF($B45="","",SUM(C45:F45)) -> 10 | AB45: =IF('Project Tracker'!D47="","",IF(COUNTIF('Project Tracker'!$D$2:D47,'Project Tracker'!D47)=1,MAX($AB$1:AB44)+1,""))
B46: =IFERROR(INDEX('Project Tracker'!$D$2:$D$5040,MATCH(32,$AB$2:$AB$5000,0)),"") -> Dimple | C46: =IF($B46="","",COUNTIFS(ProjectTracker[Auditor],$B46,ProjectTracker[Project Status],"Not Started")) -> 0 | D46: =IF($B46="","",COUNTIFS(ProjectTracker[Auditor],$B46,ProjectTracker[Project Status],"In Progress")) -> 4 | E46: =IF($B46="","",COUNTIFS(ProjectTracker[Auditor],$B46,ProjectTracker[Project Status],"Hold")) -> 1 | F46: =IF($B46="","",COUNTIFS(ProjectTracker[Auditor],$B46,ProjectTracker[Project Status],"Completed")) -> 19 | G46: =IF($B46="","",SUM(C46:F46)) -> 24 | AB46: =IF('Project Tracker'!D48="","",IF(COUNTIF('Project Tracker'!$D$2:D48,'Project Tracker'!D48)=1,MAX($AB$1:AB45)+1,""))
B47: =IFERROR(INDEX('Project Tracker'!$D$2:$D$5040,MATCH(33,$AB$2:$AB$5000,0)),"") -> Vineet | C47: =IF($B47="","",COUNTIFS(ProjectTracker[Auditor],$B47,ProjectTracker[Project Status],"Not Started")) -> 4 | D47: =IF($B47="","",COUNTIFS(ProjectTracker[Auditor],$B47,ProjectTracker[Project Status],"In Progress")) -> 4 | E47: =IF($B47="","",COUNTIFS(ProjectTracker[Auditor],$B47,ProjectTracker[Project Status],"Hold")) -> 1 | F47: =IF($B47="","",COUNTIFS(ProjectTracker[Auditor],$B47,ProjectTracker[Project Status],"Completed")) -> 10 | G47: =IF($B47="","",SUM(C47:F47)) -> 19 | AB47: =IF('Project Tracker'!D49="","",IF(COUNTIF('Project Tracker'!$D$2:D49,'Project Tracker'!D49)=1,MAX($AB$1:AB46)+1,""))
B48: =IFERROR(INDEX('Project Tracker'!$D$2:$D$5040,MATCH(34,$AB$2:$AB$5000,0)),"") -> Yash | C48: =IF($B48="","",COUNTIFS(ProjectTracker[Auditor],$B48,ProjectTracker[Project Status],"Not Started")) -> 0 | D48: =IF($B48="","",COUNTIFS(ProjectTracker[Auditor],$B48,ProjectTracker[Project Status],"In Progress")) -> 0 | E48: =IF($B48="","",COUNTIFS(ProjectTracker[Auditor],$B48,ProjectTracker[Project Status],"Hold")) -> 0 | F48: =IF($B48="","",COUNTIFS(ProjectTracker[Auditor],$B48,ProjectTracker[Project Status],"Completed")) -> 2 | G48: =IF($B48="","",SUM(C48:F48)) -> 2 | AB48: =IF('Project Tracker'!D50="","",IF(COUNTIF('Project Tracker'!$D$2:D50,'Project Tracker'!D50)=1,MAX($AB$1:AB47)+1,""))
B49: =IFERROR(INDEX('Project Tracker'!$D$2:$D$5040,MATCH(35,$AB$2:$AB$5000,0)),"") -> Zubeda | C49: =IF($B49="","",COUNTIFS(ProjectTracker[Auditor],$B49,ProjectTracker[Project Status],"Not Started")) -> 1 | D49: =IF($B49="","",COUNTIFS(ProjectTracker[Auditor],$B49,ProjectTracker[Project Status],"In Progress")) -> 13 | E49: =IF($B49="","",COUNTIFS(ProjectTracker[Auditor],$B49,ProjectTracker[Project Status],"Hold")) -> 1 | F49: =IF($B49="","",COUNTIFS(ProjectTracker[Auditor],$B49,ProjectTracker[Project Status],"Completed")) -> 7 | G49: =IF($B49="","",SUM(C49:F49)) -> 22 | AB49: =IF('Project Tracker'!D51="","",IF(COUNTIF('Project Tracker'!$D$2:D51,'Project Tracker'!D51)=1,MAX($AB$1:AB48)+1,""))
B50: =IFERROR(INDEX('Project Tracker'!$D$2:$D$5040,MATCH(36,$AB$2:$AB$5000,0)),"") -> Akash | C50: =IF($B50="","",COUNTIFS(ProjectTracker[Auditor],$B50,ProjectTracker[Project Status],"Not Started")) -> 0 | D50: =IF($B50="","",COUNTIFS(ProjectTracker[Auditor],$B50,ProjectTracker[Project Status],"In Progress")) -> 12 | E50: =IF($B50="","",COUNTIFS(ProjectTracker[Auditor],$B50,ProjectTracker[Project Status],"Hold")) -> 0 | F50: =IF($B50="","",COUNTIFS(ProjectTracker[Auditor],$B50,ProjectTracker[Project Status],"Completed")) -> 4 | G50: =IF($B50="","",SUM(C50:F50)) -> 16 | AB50: =IF('Project Tracker'!D52="","",IF(COUNTIF('Project Tracker'!$D$2:D52,'Project Tracker'!D52)=1,MAX($AB$1:AB49)+1,""))
B51: =IFERROR(INDEX('Project Tracker'!$D$2:$D$5040,MATCH(37,$AB$2:$AB$5000,0)),"") -> Akash | C51: =IF($B51="","",COUNTIFS(ProjectTracker[Auditor],$B51,ProjectTracker[Project Status],"Not Started")) -> 0 | D51: =IF($B51="","",COUNTIFS(ProjectTracker[Auditor],$B51,ProjectTracker[Project Status],"In Progress")) -> 12 | E51: =IF($B51="","",COUNTIFS(ProjectTracker[Auditor],$B51,ProjectTracker[Project Status],"Hold")) -> 0 | F51: =IF($B51="","",COUNTIFS(ProjectTracker[Auditor],$B51,ProjectTracker[Project Status],"Completed")) -> 4 | G51: =IF($B51="","",SUM(C51:F51)) -> 16 | AB51: =IF('Project Tracker'!D53="","",IF(COUNTIF('Project Tracker'!$D$2:D53,'Project Tracker'!D53)=1,MAX($AB$1:AB50)+1,""))
B52: =IFERROR(INDEX('Project Tracker'!$D$2:$D$5040,MATCH(38,$AB$2:$AB$5000,0)),"") -> Aishwarya | C52: =IF($B52="","",COUNTIFS(ProjectTracker[Auditor],$B52,ProjectTracker[Project Status],"Not Started")) -> 0 | D52: =IF($B52="","",COUNTIFS(ProjectTracker[Auditor],$B52,ProjectTracker[Project Status],"In Progress")) -> 7 | E52: =IF($B52="","",COUNTIFS(ProjectTracker[Auditor],$B52,ProjectTracker[Project Status],"Hold")) -> 0 | F52: =IF($B52="","",COUNTIFS(ProjectTracker[Auditor],$B52,ProjectTracker[Project Status],"Completed")) -> 0 | G52: =IF($B52="","",SUM(C52:F52)) -> 7 | AB52: =IF('Project Tracker'!D54="","",IF(COUNTIF('Project Tracker'!$D$2:D54,'Project Tracker'!D54)=1,MAX($AB$1:AB51)+1,""))
B53: =IFERROR(INDEX('Project Tracker'!$D$2:$D$5040,MATCH(39,$AB$2:$AB$5000,0)),"") -> Aditya | C53: =IF($B53="","",COUNTIFS(ProjectTracker[Auditor],$B53,ProjectTracker[Project Status],"Not Started")) -> 0 | D53: =IF($B53="","",COUNTIFS(ProjectTracker[Auditor],$B53,ProjectTracker[Project Status],"In Progress")) -> 5 | E53: =IF($B53="","",COUNTIFS(ProjectTracker[Auditor],$B53,ProjectTracker[Project Status],"Hold")) -> 0 | F53: =IF($B53="","",COUNTIFS(ProjectTracker[Auditor],$B53,ProjectTracker[Project Status],"Completed")) -> 2 | G53: =IF($B53="","",SUM(C53:F53)) -> 7 | AB53: =IF('Project Tracker'!D55="","",IF(COUNTIF('Project Tracker'!$D$2:D55,'Project Tracker'!D55)=1,MAX($AB$1:AB52)+1,""))
B54: =IFERROR(INDEX('Project Tracker'!$D$2:$D$5040,MATCH(40,$AB$2:$AB$5000,0)),"") -> Krishnapal | C54: =IF($B54="","",COUNTIFS(ProjectTracker[Auditor],$B54,ProjectTracker[Project Status],"Not Started")) -> 1 | D54: =IF($B54="","",COUNTIFS(ProjectTracker[Auditor],$B54,ProjectTracker[Project Status],"In Progress")) -> 17 | E54: =IF($B54="","",COUNTIFS(ProjectTracker[Auditor],$B54,ProjectTracker[Project Status],"Hold")) -> 0 | F54: =IF($B54="","",COUNTIFS(ProjectTracker[Auditor],$B54,ProjectTracker[Project Status],"Completed")) -> 2 | G54: =IF($B54="","",SUM(C54:F54)) -> 20 | AB54: =IF('Project Tracker'!D56="","",IF(COUNTIF('Project Tracker'!$D$2:D56,'Project Tracker'!D56)=1,MAX($AB$1:AB53)+1,"")) -> 14
B55: =IFERROR(INDEX('Project Tracker'!$D$2:$D$5040,MATCH(41,$AB$2:$AB$5000,0)),"") -> Jayneel Chokshi | C55: =IF($B55="","",COUNTIFS(ProjectTracker[Auditor],$B55,ProjectTracker[Project Status],"Not Started")) -> 0 | D55: =IF($B55="","",COUNTIFS(ProjectTracker[Auditor],$B55,ProjectTracker[Project Status],"In Progress")) -> 3 | E55: =IF($B55="","",COUNTIFS(ProjectTracker[Auditor],$B55,ProjectTracker[Project Status],"Hold")) -> 0 | F55: =IF($B55="","",COUNTIFS(ProjectTracker[Auditor],$B55,ProjectTracker[Project Status],"Completed")) -> 8 | G55: =IF($B55="","",SUM(C55:F55)) -> 11 | AB55: =IF('Project Tracker'!D57="","",IF(COUNTIF('Project Tracker'!$D$2:D57,'Project Tracker'!D57)=1,MAX($AB$1:AB54)+1,""))
B56: =IFERROR(INDEX('Project Tracker'!$D$2:$D$5040,MATCH(42,$AB$2:$AB$5000,0)),"") -> Owesh | C56: =IF($B56="","",COUNTIFS(ProjectTracker[Auditor],$B56,ProjectTracker[Project Status],"Not Started")) -> 0 | D56: =IF($B56="","",COUNTIFS(ProjectTracker[Auditor],$B56,ProjectTracker[Project Status],"In Progress")) -> 9 | E56: =IF($B56="","",COUNTIFS(ProjectTracker[Auditor],$B56,ProjectTracker[Project Status],"Hold")) -> 0 | F56: =IF($B56="","",COUNTIFS(ProjectTracker[Auditor],$B56,ProjectTracker[Project Status],"Completed")) -> 3 | G56: =IF($B56="","",SUM(C56:F56)) -> 12 | AB56: =IF('Project Tracker'!D58="","",IF(COUNTIF('Project Tracker'!$D$2:D58,'Project Tracker'!D58)=1,MAX($AB$1:AB55)+1,""))
B57: =IFERROR(INDEX('Project Tracker'!$D$2:$D$5040,MATCH(43,$AB$2:$AB$5000,0)),"") -> Anushree | C57: =IF($B57="","",COUNTIFS(ProjectTracker[Auditor],$B57,ProjectTracker[Project Status],"Not Started")) -> 0 | D57: =IF($B57="","",COUNTIFS(ProjectTracker[Auditor],$B57,ProjectTracker[Project Status],"In Progress")) -> 4 | E57: =IF($B57="","",COUNTIFS(ProjectTracker[Auditor],$B57,ProjectTracker[Project Status],"Hold")) -> 0 | F57: =IF($B57="","",COUNTIFS(ProjectTracker[Auditor],$B57,ProjectTracker[Project Status],"Completed")) -> 9 | G57: =IF($B57="","",SUM(C57:F57)) -> 13 | AB57: =IF('Project Tracker'!D59="","",IF(COUNTIF('Project Tracker'!$D$2:D59,'Project Tracker'!D59)=1,MAX($AB$1:AB56)+1,""))
B58: =IFERROR(INDEX('Project Tracker'!$D$2:$D$5040,MATCH(44,$AB$2:$AB$5000,0)),"") -> Kavish | C58: =IF($B58="","",COUNTIFS(ProjectTracker[Auditor],$B58,ProjectTracker[Project Status],"Not Started")) -> 0 | D58: =IF($B58="","",COUNTIFS(ProjectTracker[Auditor],$B58,ProjectTracker[Project Status],"In Progress")) -> 12 | E58: =IF($B58="","",COUNTIFS(ProjectTracker[Auditor],$B58,ProjectTracker[Project Status],"Hold")) -> 0 | F58: =IF($B58="","",COUNTIFS(ProjectTracker[Auditor],$B58,ProjectTracker[Project Status],"Completed")) -> 3 | G58: =IF($B58="","",SUM(C58:F58)) -> 15 | AB58: =IF('Project Tracker'!D60="","",IF(COUNTIF('Project Tracker'!$D$2:D60,'Project Tracker'!D60)=1,MAX($AB$1:AB57)+1,"")) -> 15
B59: =IFERROR(INDEX('Project Tracker'!$D$2:$D$5040,MATCH(45,$AB$2:$AB$5000,0)),"") | C59: =IF($B59="","",COUNTIFS(ProjectTracker[Auditor],$B59,ProjectTracker[Project Status],"Not Started")) | D59: =IF($B59="","",COUNTIFS(ProjectTracker[Auditor],$B59,ProjectTracker[Project Status],"In Progress")) | E59: =IF($B59="","",COUNTIFS(ProjectTracker[Auditor],$B59,ProjectTracker[Project Status],"Hold")) | F59: =IF($B59="","",COUNTIFS(ProjectTracker[Auditor],$B59,ProjectTracker[Project Status],"Completed")) | G59: =IF($B59="","",SUM(C59:F59)) | AB59: =IF('Project Tracker'!D61="","",IF(COUNTIF('Project Tracker'!$D$2:D61,'Project Tracker'!D61)=1,MAX($AB$1:AB58)+1,""))
B60: =IFERROR(INDEX('Project Tracker'!$D$2:$D$5040,MATCH(46,$AB$2:$AB$5000,0)),"") | C60: =IF($B60="","",COUNTIFS(ProjectTracker[Auditor],$B60,ProjectTracker[Project Status],"Not Started")) | D60: =IF($B60="","",COUNTIFS(ProjectTracker[Auditor],$B60,ProjectTracker[Project Status],"In Progress")) | E60: =IF($B60="","",COUNTIFS(ProjectTracker[Auditor],$B60,ProjectTracker[Project Status],"Hold")) | F60: =IF($B60="","",COUNTIFS(ProjectTracker[Auditor],$B60,ProjectTracker[Project Status],"Completed")) | G60: =IF($B60="","",SUM(C60:F60)) | AB60: =IF('Project Tracker'!D62="","",IF(COUNTIF('Project Tracker'!$D$2:D62,'Project Tracker'!D62)=1,MAX($AB$1:AB59)+1,""))
B61: =IFERROR(INDEX('Project Tracker'!$D$2:$D$5040,MATCH(47,$AB$2:$AB$5000,0)),"") | C61: =IF($B61="","",COUNTIFS(ProjectTracker[Auditor],$B61,ProjectTracker[Project Status],"Not Started")) | D61: =IF($B61="","",COUNTIFS(ProjectTracker[Auditor],$B61,ProjectTracker[Project Status],"In Progress")) | E61: =IF($B61="","",COUNTIFS(ProjectTracker[Auditor],$B61,ProjectTracker[Project Status],"Hold")) | F61: =IF($B61="","",COUNTIFS(ProjectTracker[Auditor],$B61,ProjectTracker[Project Status],"Completed")) | G61: =IF($B61="","",SUM(C61:F61)) | AB61: =IF('Project Tracker'!D63="","",IF(COUNTIF('Project Tracker'!$D$2:D63,'Project Tracker'!D63)=1,MAX($AB$1:AB60)+1,""))
B62: =IFERROR(INDEX('Project Tracker'!$D$2:$D$5040,MATCH(48,$AB$2:$AB$5000,0)),"") | C62: =IF($B62="","",COUNTIFS(ProjectTracker[Auditor],$B62,ProjectTracker[Project Status],"Not Started")) | D62: =IF($B62="","",COUNTIFS(ProjectTracker[Auditor],$B62,ProjectTracker[Project Status],"In Progress")) | E62: =IF($B62="","",COUNTIFS(ProjectTracker[Auditor],$B62,ProjectTracker[Project Status],"Hold")) | F62: =IF($B62="","",COUNTIFS(ProjectTracker[Auditor],$B62,ProjectTracker[Project Status],"Completed")) | G62: =IF($B62="","",SUM(C62:F62)) | AB62: =IF('Project Tracker'!D64="","",IF(COUNTIF('Project Tracker'!$D$2:D326,'Project Tracker'!D64)=1,MAX($AB$1:AB61)+1,"")) -> 16
B63: =IFERROR(INDEX('Project Tracker'!$D$2:$D$5040,MATCH(49,$AB$2:$AB$5000,0)),"") | C63: =IF($B63="","",COUNTIFS(ProjectTracker[Auditor],$B63,ProjectTracker[Project Status],"Not Started")) | D63: =IF($B63="","",COUNTIFS(ProjectTracker[Auditor],$B63,ProjectTracker[Project Status],"In Progress")) | E63: =IF($B63="","",COUNTIFS(ProjectTracker[Auditor],$B63,ProjectTracker[Project Status],"Hold")) | F63: =IF($B63="","",COUNTIFS(ProjectTracker[Auditor],$B63,ProjectTracker[Project Status],"Completed")) | G63: =IF($B63="","",SUM(C63:F63)) | AB63: =IF('Project Tracker'!D65="","",IF(COUNTIF('Project Tracker'!$D$2:D65,'Project Tracker'!D65)=1,MAX($AB$1:AB62)+1,""))
B64: =IFERROR(INDEX('Project Tracker'!$D$2:$D$5040,MATCH(50,$AB$2:$AB$5000,0)),"") | C64: =IF($B64="","",COUNTIFS(ProjectTracker[Auditor],$B64,ProjectTracker[Project Status],"Not Started")) | D64: =IF($B64="","",COUNTIFS(ProjectTracker[Auditor],$B64,ProjectTracker[Project Status],"In Progress")) | E64: =IF($B64="","",COUNTIFS(ProjectTracker[Auditor],$B64,ProjectTracker[Project Status],"Hold")) | F64: =IF($B64="","",COUNTIFS(ProjectTracker[Auditor],$B64,ProjectTracker[Project Status],"Completed")) | G64: =IF($B64="","",SUM(C64:F64)) | AB64: =IF('Project Tracker'!D66="","",IF(COUNTIF('Project Tracker'!$D$2:D66,'Project Tracker'!D66)=1,MAX($AB$1:AB63)+1,"")) -> 17
B65: =IFERROR(INDEX('Project Tracker'!$D$2:$D$5040,MATCH(51,$AB$2:$AB$5000,0)),"") | C65: =IF($B65="","",COUNTIFS(ProjectTracker[Auditor],$B65,ProjectTracker[Project Status],"Not Started")) | D65: =IF($B65="","",COUNTIFS(ProjectTracker[Auditor],$B65,ProjectTracker[Project Status],"In Progress")) | E65: =IF($B65="","",COUNTIFS(ProjectTracker[Auditor],$B65,ProjectTracker[Project Status],"Hold")) | F65: =IF($B65="","",COUNTIFS(ProjectTracker[Auditor],$B65,ProjectTracker[Project Status],"Completed")) | G65: =IF($B65="","",SUM(C65:F65)) | AB65: =IF('Project Tracker'!D67="","",IF(COUNTIF('Project Tracker'!$D$2:D67,'Project Tracker'!D67)=1,MAX($AB$1:AB64)+1,"")) -> 18
B66: =IFERROR(INDEX('Project Tracker'!$D$2:$D$5040,MATCH(52,$AB$2:$AB$5000,0)),"") | C66: =IF($B66="","",COUNTIFS(ProjectTracker[Auditor],$B66,ProjectTracker[Project Status],"Not Started")) | D66: =IF($B66="","",COUNTIFS(ProjectTracker[Auditor],$B66,ProjectTracker[Project Status],"In Progress")) | E66: =IF($B66="","",COUNTIFS(ProjectTracker[Auditor],$B66,ProjectTracker[Project Status],"Hold")) | F66: =IF($B66="","",COUNTIFS(ProjectTracker[Auditor],$B66,ProjectTracker[Project Status],"Completed")) | G66: =IF($B66="","",SUM(C66:F66)) | AB66: =IF('Project Tracker'!D68="","",IF(COUNTIF('Project Tracker'!$D$2:D68,'Project Tracker'!D68)=1,MAX($AB$1:AB65)+1,""))
B67: =IFERROR(INDEX('Project Tracker'!$D$2:$D$5040,MATCH(53,$AB$2:$AB$5000,0)),"") | C67: =IF($B67="","",COUNTIFS(ProjectTracker[Auditor],$B67,ProjectTracker[Project Status],"Not Started")) | D67: =IF($B67="","",COUNTIFS(ProjectTracker[Auditor],$B67,ProjectTracker[Project Status],"In Progress")) | E67: =IF($B67="","",COUNTIFS(ProjectTracker[Auditor],$B67,ProjectTracker[Project Status],"Hold")) | F67: =IF($B67="","",COUNTIFS(ProjectTracker[Auditor],$B67,ProjectTracker[Project Status],"Completed")) | G67: =IF($B67="","",SUM(C67:F67)) | AB67: =IF('Project Tracker'!D69="","",IF(COUNTIF('Project Tracker'!$D$2:D69,'Project Tracker'!D69)=1,MAX($AB$1:AB66)+1,"")) -> 19
B68: =IFERROR(INDEX('Project Tracker'!$D$2:$D$5040,MATCH(54,$AB$2:$AB$5000,0)),"") | C68: =IF($B68="","",COUNTIFS(ProjectTracker[Auditor],$B68,ProjectTracker[Project Status],"Not Started")) | D68: =IF($B68="","",COUNTIFS(ProjectTracker[Auditor],$B68,ProjectTracker[Project Status],"In Progress")) | E68: =IF($B68="","",COUNTIFS(ProjectTracker[Auditor],$B68,ProjectTracker[Project Status],"Hold")) | F68: =IF($B68="","",COUNTIFS(ProjectTracker[Auditor],$B68,ProjectTracker[Project Status],"Completed")) | G68: =IF($B68="","",SUM(C68:F68)) | AB68: =IF('Project Tracker'!D70="","",IF(COUNTIF('Project Tracker'!$D$2:D70,'Project Tracker'!D70)=1,MAX($AB$1:AB67)+1,"")) -> 20
B69: =IFERROR(INDEX('Project Tracker'!$D$2:$D$5040,MATCH(55,$AB$2:$AB$5000,0)),"") | C69: =IF($B69="","",COUNTIFS(ProjectTracker[Auditor],$B69,ProjectTracker[Project Status],"Not Started")) | D69: =IF($B69="","",COUNTIFS(ProjectTracker[Auditor],$B69,ProjectTracker[Project Status],"In Progress")) | E69: =IF($B69="","",COUNTIFS(ProjectTracker[Auditor],$B69,ProjectTracker[Project Status],"Hold")) | F69: =IF($B69="","",COUNTIFS(ProjectTracker[Auditor],$B69,ProjectTracker[Project Status],"Completed")) | G69: =IF($B69="","",SUM(C69:F69)) | AB69: =IF('Project Tracker'!D71="","",IF(COUNTIF('Project Tracker'!$D$2:D71,'Project Tracker'!D71)=1,MAX($AB$1:AB68)+1,""))
B70: =IFERROR(INDEX('Project Tracker'!$D$2:$D$5040,MATCH(56,$AB$2:$AB$5000,0)),"") | C70: =IF($B70="","",COUNTIFS(ProjectTracker[Auditor],$B70,ProjectTracker[Project Status],"Not Started")) | D70: =IF($B70="","",COUNTIFS(ProjectTracker[Auditor],$B70,ProjectTracker[Project Status],"In Progress")) | E70: =IF($B70="","",COUNTIFS(ProjectTracker[Auditor],$B70,ProjectTracker[Project Status],"Hold")) | F70: =IF($B70="","",COUNTIFS(ProjectTracker[Auditor],$B70,ProjectTracker[Project Status],"Completed")) | G70: =IF($B70="","",SUM(C70:F70)) | AB70: =IF('Project Tracker'!D72="","",IF(COUNTIF('Project Tracker'!$D$2:D72,'Project Tracker'!D72)=1,MAX($AB$1:AB69)+1,"")) -> 21
B71: =IFERROR(INDEX('Project Tracker'!$D$2:$D$5040,MATCH(57,$AB$2:$AB$5000,0)),"") | C71: =IF($B71="","",COUNTIFS(ProjectTracker[Auditor],$B71,ProjectTracker[Project Status],"Not Started")) | D71: =IF($B71="","",COUNTIFS(ProjectTracker[Auditor],$B71,ProjectTracker[Project Status],"In Progress")) | E71: =IF($B71="","",COUNTIFS(ProjectTracker[Auditor],$B71,ProjectTracker[Project Status],"Hold")) | F71: =IF($B71="","",COUNTIFS(ProjectTracker[Auditor],$B71,ProjectTracker[Project Status],"Completed")) | G71: =IF($B71="","",SUM(C71:F71)) | AB71: =IF('Project Tracker'!D73="","",IF(COUNTIF('Project Tracker'!$D$2:D73,'Project Tracker'!D73)=1,MAX($AB$1:AB70)+1,""))
B72: =IFERROR(INDEX('Project Tracker'!$D$2:$D$5040,MATCH(58,$AB$2:$AB$5000,0)),"") | C72: =IF($B72="","",COUNTIFS(ProjectTracker[Auditor],$B72,ProjectTracker[Project Status],"Not Started")) | D72: =IF($B72="","",COUNTIFS(ProjectTracker[Auditor],$B72,ProjectTracker[Project Status],"In Progress")) | E72: =IF($B72="","",COUNTIFS(ProjectTracker[Auditor],$B72,ProjectTracker[Project Status],"Hold")) | F72: =IF($B72="","",COUNTIFS(ProjectTracker[Auditor],$B72,ProjectTracker[Project Status],"Completed")) | G72: =IF($B72="","",SUM(C72:F72)) | AB72: =IF('Project Tracker'!D74="","",IF(COUNTIF('Project Tracker'!$D$2:D74,'Project Tracker'!D74)=1,MAX($AB$1:AB71)+1,""))
B73: =IFERROR(INDEX('Project Tracker'!$D$2:$D$5040,MATCH(59,$AB$2:$AB$5000,0)),"") | C73: =IF($B73="","",COUNTIFS(ProjectTracker[Auditor],$B73,ProjectTracker[Project Status],"Not Started")) | D73: =IF($B73="","",COUNTIFS(ProjectTracker[Auditor],$B73,ProjectTracker[Project Status],"In Progress")) | E73: =IF($B73="","",COUNTIFS(ProjectTracker[Auditor],$B73,ProjectTracker[Project Status],"Hold")) | F73: =IF($B73="","",COUNTIFS(ProjectTracker[Auditor],$B73,ProjectTracker[Project Status],"Completed")) | G73: =IF($B73="","",SUM(C73:F73)) | AB73: =IF('Project Tracker'!D75="","",IF(COUNTIF('Project Tracker'!$D$2:D75,'Project Tracker'!D75)=1,MAX($AB$1:AB72)+1,""))
B74: =IFERROR(INDEX('Project Tracker'!$D$2:$D$5040,MATCH(60,$AB$2:$AB$5000,0)),"") | C74: =IF($B74="","",COUNTIFS(ProjectTracker[Auditor],$B74,ProjectTracker[Project Status],"Not Started")) | D74: =IF($B74="","",COUNTIFS(ProjectTracker[Auditor],$B74,ProjectTracker[Project Status],"In Progress")) | E74: =IF($B74="","",COUNTIFS(ProjectTracker[Auditor],$B74,ProjectTracker[Project Status],"Hold")) | F74: =IF($B74="","",COUNTIFS(ProjectTracker[Auditor],$B74,ProjectTracker[Project Status],"Completed")) | G74: =IF($B74="","",SUM(C74:F74)) | AB74: =IF('Project Tracker'!D76="","",IF(COUNTIF('Project Tracker'!$D$2:D76,'Project Tracker'!D76)=1,MAX($AB$1:AB73)+1,""))
AB75: =IF('Project Tracker'!D77="","",IF(COUNTIF('Project Tracker'!$D$2:D77,'Project Tracker'!D77)=1,MAX($AB$1:AB74)+1,""))
B76: Space is reserved above for up to 60 auditors. To support more, extend the formulas in columns B:G down as needed. | AB76: =IF('Project Tracker'!D78="","",IF(COUNTIF('Project Tracker'!$D$2:D78,'Project Tracker'!D78)=1,MAX($AB$1:AB75)+1,""))
AB77: =IF('Project Tracker'!D79="","",IF(COUNTIF('Project Tracker'!$D$2:D79,'Project Tracker'!D79)=1,MAX($AB$1:AB76)+1,"")) -> 22
AB78: =IF('Project Tracker'!D80="","",IF(COUNTIF('Project Tracker'!$D$2:D80,'Project Tracker'!D80)=1,MAX($AB$1:AB77)+1,"")) -> 23
AB79: =IF('Project Tracker'!D81="","",IF(COUNTIF('Project Tracker'!$D$2:D81,'Project Tracker'!D81)=1,MAX($AB$1:AB78)+1,"")) -> 24
AB80: =IF('Project Tracker'!D82="","",IF(COUNTIF('Project Tracker'!$D$2:D82,'Project Tracker'!D82)=1,MAX($AB$1:AB79)+1,""))
AB81: =IF('Project Tracker'!D83="","",IF(COUNTIF('Project Tracker'!$D$2:D83,'Project Tracker'!D83)=1,MAX($AB$1:AB80)+1,""))
AB82: =IF('Project Tracker'!D84="","",IF(COUNTIF('Project Tracker'!$D$2:D84,'Project Tracker'!D84)=1,MAX($AB$1:AB81)+1,"")) -> 25
AB83: =IF('Project Tracker'!D85="","",IF(COUNTIF('Project Tracker'!$D$2:D85,'Project Tracker'!D85)=1,MAX($AB$1:AB82)+1,""))
AB84: =IF('Project Tracker'!D86="","",IF(COUNTIF('Project Tracker'!$D$2:D86,'Project Tracker'!D86)=1,MAX($AB$1:AB83)+1,""))
AB85: =IF('Project Tracker'!D87="","",IF(COUNTIF('Project Tracker'!$D$2:D87,'Project Tracker'!D87)=1,MAX($AB$1:AB84)+1,""))
AB86: =IF('Project Tracker'!D88="","",IF(COUNTIF('Project Tracker'!$D$2:D88,'Project Tracker'!D88)=1,MAX($AB$1:AB85)+1,"")) -> 26
AB87: =IF('Project Tracker'!D89="","",IF(COUNTIF('Project Tracker'!$D$2:D89,'Project Tracker'!D89)=1,MAX($AB$1:AB86)+1,""))
AB88: =IF('Project Tracker'!D90="","",IF(COUNTIF('Project Tracker'!$D$2:D90,'Project Tracker'!D90)=1,MAX($AB$1:AB87)+1,""))
... AB177: =IF('Project Tracker'!D179="","",IF(COUNTIF('Project Tracker'!$D$2:D179,'Project Tracker'!D179)=1,MAX($AB$1:AB176)+1,""))
AB178: =IF('Project Tracker'!D180="","",IF(COUNTIF('Project Tracker'!$D$2:D326,'Project Tracker'!D180)=1,MAX($AB$1:AB177)+1,""))
AB179: =IF('Project Tracker'!D181="","",IF(COUNTIF('Project Tracker'!$D$2:D181,'Project Tracker'!D181)=1,MAX($AB$1:AB178)+1,""))
AB180: =IF('Project Tracker'!D182="","",IF(COUNTIF('Project Tracker'!$D$2:D182,'Project Tracker'!D182)=1,MAX($AB$1:AB179)+1,"")) -> 41
AB181: =IF('Project Tracker'!D183="","",IF(COUNTIF('Project Tracker'!$D$2:D183,'Project Tracker'!D183)=1,MAX($AB$1:AB180)+1,""))
AB182: =IF('Project Tracker'!D184="","",IF(COUNTIF('Project Tracker'!$D$2:D184,'Project Tracker'!D184)=1,MAX($AB$1:AB181)+1,""))
AB183: =IF('Project Tracker'!D185="","",IF(COUNTIF('Project Tracker'!$D$2:D185,'Project Tracker'!D185)=1,MAX($AB$1:AB182)+1,""))
AB184: =IF('Project Tracker'!D186="","",IF(COUNTIF('Project Tracker'!$D$2:D186,'Project Tracker'!D186)=1,MAX($AB$1:AB183)+1,""))
AB185: =IF('Project Tracker'!D187="","",IF(COUNTIF('Project Tracker'!$D$2:D187,'Project Tracker'!D187)=1,MAX($AB$1:AB184)+1,""))
AB186: =IF('Project Tracker'!D188="","",IF(COUNTIF('Project Tracker'!$D$2:D188,'Project Tracker'!D188)=1,MAX($AB$1:AB185)+1,"")) -> 42
AB187: =IF('Project Tracker'!D189="","",IF(COUNTIF('Project Tracker'!$D$2:D189,'Project Tracker'!D189)=1,MAX($AB$1:AB186)+1,""))
AB188: =IF('Project Tracker'!D190="","",IF(COUNTIF('Project Tracker'!$D$2:D190,'Project Tracker'!D190)=1,MAX($AB$1:AB187)+1,""))
...

Sheet Project Tracker
A1: SR No. | B1: Client Name | C1: Type of Audit | D1: Auditor | E1: Cert-IN ID | F1: Doc ID No. | G1: Project Status | H1: Category | I1: Description | J1: BD | K1: Created Date | L1: Initial Gap Assessment Report Release Date | M1: Metadata of Initial Gap Assessment Report | N1: Closure Report Release Date | O1: Metadata of Closure Report | P1: Payment Confirmation | Q1: Report Prepared By | R1: Report Reviewed By | S1: Remarks
A2: 1 | B2: Astral | C2: Assessment | D2: Dimple | G2: Completed | H2: Enterprise | K2: 46062 | P2: Yes
A3: 2 | B3: Adani Airport - NMIAL | C3: ISO 27001 | D3: Gautam Patidar | G3: In Progress | H3: Enterprise | K3: 46009 | P3: No
A4: 3 | B4: Adani Airport - Mangalore | C4: ISO 27001 | D4: Gautam Patidar | G4: In Progress | H4: Enterprise | K4: 46009 | P4: No
A5: 4 | B5: Airport - TRV | C5: ISO 27001 | D5: Gautam Patidar | G5: In Progress | H5: Enterprise
A6: 5 | B6: Airport - Ahm | C6: ISO 27001 | D6: Gautam Patidar | G6: In Progress | H6: Enterprise
A7: 6 | B7: ETP Group - PCI SSS | C7: PCI SSS | D7: Gautam Patidar | G7: In Progress | H7: Enterprise | K7: 46001 | P7: No
A8: 7 | B8: ETP Group - PCI SSS | C8: PCI DSS | D8: Gautam Patidar | G8: Completed | H8: Enterprise | K8: 46001 | P8: Yes
A9: 8 | B9: Vidal Health | C9: SOC 2 | D9: Akash | G9: Completed | H9: Enterprise | K9: 45707 | P9: Yes
A10: 9 | B10: Adani Total Gas Limited and IOAGPL | C10: ISO 27001 | D10: Gautam Patidar, Anushree Pillai | G10: In Progress | H10: Enterprise | K10: 45965 | P10: No
A11: 10 | B11: Vigilhawk Labs | C11: ISO 9001 | D11: Jayneel | G11: In Progress | H11: Enterprise | K11: 45965 | P11: No
A12: 11 | B12: Vigilhawk Labs | C12: ISO 27001 | D12: Jayneel | G12: In Progress | H12: Enterprise | K12: 45965 | P12: No
A13: 12 | B13: Vigilhawk Labs | C13: SOC 2 - Type 2 | D13: Jayneel | G13: In Progress | H13: Enterprise | K13: 45965 | P13: No
A14: 13 | B14: Amzure Unified Services | C14: ISO 9001 | D14: Jayneel | G14: In Progress | H14: Enterprise | K14: 45965 | P14: No
A15: 14 | B15: Amzure Unified Services | C15: SOC 2 - Type 2 | D15: Jayneel | G15: In Progress | H15: Enterprise | K15: 45965 | P15: No
A16: 15 | B16: Amzure Unified Services | C16: ISO 27001 | D16: Jayneel | G16: In Progress | H16: Enterprise | K16: 45965 | P16: No
A17: 16 | B17: EZScript | C17: SOC 2 | D17: Anushree | G17: In Progress | H17: Enterprise | K17: 45896 | P17: No
A18: 17 | B18: EZScript | C18: HIPPA | D18: Anushree | G18: In Progress | H18: Enterprise | K18: 45896 | P18: No
... A30: 29 | B30: Octanom Tech Private Limited | C30: (Application Approval - NSE, BSE) | D30: Jayneel Chokshi | G30: Completed | H30: Enterprise | K30: 46104 | P30: Yes
A31: 30 | B31: HOCCO | C31: Maturity Assessment | D31: Jayraj | G31: In Progress | H31: Enterprise | J31: Jamin Doshi | K31: 46115 | P31: No
A32: 31 | B32: HOCCO | C32: ISO 27001 | D32: Jayraj | G32: In Progress | H32: Enterprise | J32: Jamin Doshi | K32: 46115 | P32: No
A33: 32 | B33: Inferenz Tech Private Limited - Surveillance Audit | C33: ISO 27001 | D33: Jayneel Chokshi, Akash Panchal | G33: Completed | H33: Enterprise | K33: 46118 | P33: Yes
A34: 33 | B34: JAPFA Comfeed India Pvt Ltd - Surveillance Audit | C34: ISO 27001 | D34: Jayneel Chokshi | G34: Completed | H34: Enterprise | J34: Mihir | K34: 46119 | P34: Yes
A35: 34 | B35: SandBox - ISO:27001 Renewal (Certification) (Sandbox's ISO 27001:2022 Re-certification Audit) | C35: ISO 27001 | D35: Dimple | G35: Completed | H35: Enterprise | J35: Ketan | K35: 46127 | P35: Yes
A36: 35 | B36: Multi Commodity Exchange Clearing Corporation Limited | C36: ISO 22301:2019 | D36: Gautam Patidar , Anushree pillai, Aditya katkar | G36: Completed | H36: Enterprise | J36: Shankhdeep | K36: 46127 | P36: Yes
A37: 36 | B37: Multi Commodity Exchange Clearing Corporation Limited | C37: ISO 27001 | D37: Gautam Patidar , Anushree pillai, Aditya katkar | G37: Completed | H37: Enterprise | J37: Shankhdeep | K37: 46127 | P37: Yes
A38: 37 | B38: Multi Commodity Exchange Clearing Corporation Limited | C38: ISO 9001 | D38: Gautam Patidar , Anushree pillai, Aditya katkar | G38: Completed | H38: Enterprise | J38: Shankhdeep | K38: 46127 | P38: Yes
A39: 38 | B39: Master Capital | C39: E-KYC | D39: Pratham | G39: In Progress | H39: Enterprise | K39: 46129 | P39: No
A40: 39 | B40: SR Algotech Private Limited - Algo Approval NSE | C40: Algo Approval Audit | D40: Tejas | G40: Not Started | H40: Enterprise | I40: Cancelled | J40: Shankhdeep | K40: 46133 | P40: No
A41: 40 | B41: SR Algotech Private Limited - Algo Approval BSE | C41: Algo Approval Audit | D41: Tejas | G41: Not Started | H41: Enterprise | I41: Cancelled | J41: Shankhdeep | K41: 46133 | P41: No
A42: 41 | B42: WISEOWL SECURITIES PRIVATE LIMITED (Finnhancer Solutions Private Limited) | C42: E-KYC | D42: Dimple | G42: Hold | H42: Enterprise | J42: Shankhdeep | K42: 46134 | P42: No
A43: 42 | B43: Societe Generale | C43: GRC - Activity | D43: Dimple | G43: Completed | H43: Enterprise | J43: Shankhdeep | K43: 46154 | P43: Yes
A44: 43 | B44: INFINITY CYBERSEC PTE LTD - SOC 2 | C44: SOC 2 - Type 2 | D44: Akash | G44: Completed | H44: Enterprise | K44: 46061 | P44: Yes
A45: 44 | B45: Sunidhi Securities & Finance Ltd - GRC ACTIVITY | C45: GRC - Activity | D45: Dimple | G45: Completed | H45: Enterprise | K45: 46099 | P45: Yes
A46: 45 | B46: Gretex Broking- IBT & STWT BSE F&O | C46: APPLICATION APPROVAL | D46: Dimple | G46: Completed | H46: Enterprise | K46: 45966 | P46: Yes
A47: 46 | B47: SUMANEL TECHNOLOGY VENTURES PVT LTD - SOC 2 | C47: SOC 2 - Type 2 | D47: Jayneel Chokshi | G47: Completed | H47: Enterprise | K47: Dec 2,2025 | P47: Yes
A48: 47 | B48: Chandrakala Broking Services Pvt. Ltd | C48: APPLICATION APPROVAL | D48: Dimple | G48: Completed | H48: Enterprise | K48: Mar 2,2025 | P48: Yes
A49: 48 | B49: Sunidhi Securities & Finance Ltd - Risk Assessment | C49: Risk Assessment | D49: Dimple | G49: Completed | H49: Enterprise | K49: Mar 18,2026 | P49: Yes
A50: 49 | B50: master trust - Application Approval | C50: APPLICATION APPROVAL | D50: Dimple | G50: Completed | H50: Enterprise | K50: 45908 | P50: Yes
A51: 50 | B51: Eureka Stock & Share Broking Services Limited | C51: APPLICATION APPROVAL | D51: Jayneel Chokshi | G51: Completed | H51: Enterprise | K51: 46063 | P51: Yes
A52: 51 | B52: Master Capital | C52: APPLICATION APPROVAL | D52: Dimple | G52: Completed | H52: Enterprise | J52: Akshar | K52: 46160 | P52: Yes
A53: 52 | B53: XTS | C53: APPLICATION APPROVAL | D53: Dimple | G53: Completed | H53: Enterprise | K53: 46167 | P53: Yes
A54: 53 | B54: JAIPUR INTERNATIONAL AIRPORT LIMITED SANGANER | C54: Maturity Assessment , GRC Actibity | D54: Jayraj | F54: TDL/JIALS/CISF/2026-27/0092 | G54: Completed | H54: Enterprise | J54: Hitisha Goyal | K54: 46177 | P54: No
A55: 54 | B55: Shree Naman Securities and Finance Pvt. Ltd | C55: E-KYC | D55: Pratham | G55: Completed | H55: Enterprise | J55: Ketan | K55: 46181 | P55: Yes
A56: 55 | B56: Futurus FinAce Consulting Private Limited | C56: ISO 27001 | D56: Jayraj, Anushree | G56: In Progress | H56: Enterprise | J56: Rushab Pawani | K56: 46181 | P56: No
A57: 56 | B57: Futurus FinAce Consulting Private Limited | C57: SOC 2 - Type 2 | D57: Jayraj, Anushree | G57: In Progress | H57: Enterprise | J57: Rushab Pawani | K57: 46181 | P57: No
A58: 57 | B58: Futurus FinAce Consulting Private Limited | C58: CMMI LEVEL 3 | D58: Jayraj, Anushree | G58: In Progress | H58: Enterprise | J58: Rushab Pawani | K58: 46181 | P58: No
A59: 58 | B59: Futurus FinAce Consulting Private Limited | C59: SOC | D59: Jayraj, Anushree | G59: In Progress | H59: Enterprise | J59: Rushab Pawani | K59: 46181 | P59: No
A60: 59 | B60: COMFORT SECURITIES LIMITED | C60: APPLICATION APPROVAL AUDIT | D60: Vineet | G60: Completed | H60: Enterprise | J60: Akshar | K60: 46195 | P60: Yes
A61: 60 | B61: SUMANEL TECHNOLOGY VENTURES PVT LTD | C61: ISO 27001:2022 | D61: Akash | G61: In Progress | H61: Enterprise | J61: Jaimin | K61: 46202 | P61: No
A62: 61 | B62: ADJ UTILITY APPS PRIVATE LIMITED (KhataBook) | C62: ISO 27001/2022 certification only and support during the external audit | D62: Gautam Patidar | G62: Completed | H62: Enterprise | J62: Akshar | K62: 46205 | P62: Yes
A63: 62 | B63: Genie InfoTech Private Limited | C63: SOC 2 - Type 2 | D63: Akash | G63: In Progress | H63: Enterprise | J63: Shankhadeep | K63: 46210 | P63: No
A64: 63 | B64: Rugr Sil Pvt Ltd. | C64: DL Secure Application Review - SAR Report -> Suvarna Laxmi Nidhi Limited | D64: Kavish | G64: Completed | H64: Enterprise | J64: Nikhil | K64: 46210 | P64: Yes
A65: 64 | B65: The Ranuj Nagrik Sahakari Bank | C65: SAQ AUDIT | D65: Alphae | G65: In Progress | H65: Bank | K65: 46037 | P65: No
A66: 65 | B66: Beawar Urban Cooperative Bank ltd | C66: SAQ AUDIT | D66: Deven | G66: Completed | H66: Bank | K66: 46059 | P66: Yes
A67: 66 | B67: Ahmednagar Shahar Sahakari Bank | C67: SAQ AUDIT | D67: Ashutosh, Anushree | G67: Completed | H67: Bank | K67: 46056 | P67: Yes
A68: 67 | B68: Dhanera Mercantile Co-Operative Bank Limited. | C68: IT/IS AUDIT | D68: Pratham | G68: In Progress | H68: Bank | K68: 45978 | P68: No
A69: 68 | B69: The Nadiad People's Co-op. Bank Ltd | C69: IT/IS AUDIT | D69: Hrishikesh | G69: In Progress | H69: Bank | K69: 45965 | P69: No
A70: 69 | B70: Progressive Mercantile Cooperative Bank | C70: IT/IS AUDIT | D70: Sagar | G70: Completed | H70: Bank | K70: 45852 | P70: Yes
A71: 70 | B71: People's Co-operative Bank Ltd Dholka | C71: SAQ AUDIT | D71: Jayneel Chokshi | G71: Completed | H71: Bank | K71: 45785 | P71: Yes
A72: 71 | B72: The Modasa Nagarik Sahakari Bank Ltd | C72: SAQ AUDIT | D72: Ehshan, Anushree | G72: Completed | H72: Bank | K72: 46080 | P72: Yes
A73: 72 | B73: The saurashtra co. op Bank Ltd | C73: SAQ AUDIT | D73: Pratham | G73: Completed | H73: Bank | K73: 46080 | P73: Yes
A74: 73 | B74: Raigad Sahakari Bank Ltd. | C74: SAQ AUDIT | D74: Vineet | G74: Hold | H74: Bank | K74: 46087 | P74: No
A75: 74 | B75: The Vyankateshwara Sahakari Bank Ltd - Gap Assesment | C75: SAQ AUDIT | D75: Ehshan, Anushree | G75: Completed | H75: Bank | K75: 46087 | N75: 46225 | P75: Yes
A76: 75 | B76: The Vyankateshwara Sahakari Bank Ltd - IS Audit (Onsite) | C76: IT/IS AUDIT | D76: Ehshan, Anushree | G76: Completed | H76: Bank | K76: 46087 | N76: 46224 | P76: Yes
A77: 76 | B77: RAJPUTANA MAHILA URBAN COOP. BANK LTD. | C77: SAQ AUDIT | D77: Anushree | G77: In Progress | H77: Bank | K77: 46094 | P77: No
A78: 77 | B78: Etawah Urban Bank (Not Applicable) | C78: SAR AUDIT | D78: Alphae | G78: Not Started | H78: Bank | J78: Akshar | K78: 46098 | P78: No
A79: 78 | B79: Jodhpur Nagrik Sahakari Bank Limited - Reassessment | C79: SAQ AUDIT | D79: Vineet, Purvi | G79: Completed | H79: Bank | K79: 46099 | P79: Yes
A80: 79 | B80: Patan Nagarik Sahakari Bank - re assessment | C80: SAQ AUDIT | D80: Jayraj, Kavish | G80: Completed | H80: Bank | K80: 46118 | P80: Yes
A81: 80 | B81: Himatnagar Nagrik Sahakari Bank Limited - Re Assessment | C81: SAQ AUDIT | D81: Jayraj , Deven | G81: Completed | H81: Bank | J81: Deven | K81: 46118 | P81: Yes
A82: 81 | B82: THE BANASKANTHA DISTRICT CENTRAL CO-OP. BANK LTD. | C82: CYBER AUDIT | D82: Pratham | G82: Completed | H82: Bank | K82: 46119 | P82: Yes
A83: 82 | B83: THE BANASKANTHA DISTRICT CENTRAL CO-OP. BANK LTD. | C83: VICS AUDIT | D83: Pratham | G83: Completed | H83: Bank | K83: 46119 | P83: Yes
A84: 83 | B84: Vijay Cooperative bank | C84: CPS AUDIT | D84: Purvi | G84: Completed | H84: Bank | K84: 46115 | P84: Yes
A85: 84 | B85: THE NEW URBAN CO-OPERATIVE BANK LTD RAMPUR | C85: SAR AUDIT | D85: Akash | G85: In Progress | H85: Bank | J85: Akshar | K85: 46126 | P85: No
A86: 85 | B86: THE NEW URBAN CO-OPERATIVE BANK LTD RAMPUR | C86: SAQ AUDIT | D86: Akash | G86: In Progress | H86: Bank | J86: Akshar | K86: 46126 | P86: No
A87: 86 | B87: THE NEW URBAN CO-OPERATIVE BANK LTD RAMPUR | C87: IT/IS AUDIT | D87: Akash | G87: In Progress | H87: Bank | I87: 3 Branches | J87: Akshar | K87: 46126 | P87: No
A88: 87 | B88: Nagrik Sahakari Bank Maryadit | C88: SAR AUDIT | D88: Krishnapal | G88: In Progress | H88: Bank | J88: Shankdeep | K88: 46132 | P88: No
A89: 88 | B89: Nagrik Sahakari Bank Maryadit | C89: SAQ AUDIT | D89: Krishnapal | G89: In Progress | H89: Bank | J89: Shankdeep | K89: 46132 | P89: No
A90: 89 | B90: Nagrik Sahakari Bank Maryadit - on site | C90: IT/IS AUDIT | D90: Krishnapal | G90: In Progress | H90: Bank | J90: Shankdeep | K90: 46132 | P90: No
A91: 90 | B91: Uttarakhand Co-Operative Bank Ltd | C91: SAQ AUDIT | D91: Akash | G91: Completed | H91: Bank | J91: Shankdeep | K91: 46132 | P91: Yes
A92: 91 | B92: Akhand Anand Co-Operative Bank Limited - Re Assessment | C92: SAQ AUDIT | D92: Vineet | G92: Completed | H92: Bank | K92: 46133 | P92: Yes
A93: 92 | B93: Gandhidham Co-operative Bank Limited - Re Assessment | C93: SAQ AUDIT | D93: Pratham | G93: Completed | H93: Bank | K93: 46134 | P93: Yes
A94: 93 | B94: Rajkot Peoples Co-operative Bank Limited - Re_Assessment | C94: SAQ AUDIT | D94: Aditya | G94: Completed | H94: Bank | K94: 46134 | P94: Yes
A95: 94 | B95: Agrasen Bank- Reassessment | C95: SAQ AUDIT | D95: Hrishikesh | G95: Completed | H95: Bank | K95: 46134 | P95: Yes
A96: 95 | B96: The Hisar Urban Cooperative Bank Ltd. | C96: SAQ AUDIT | D96: Owesh | G96: Completed | H96: Bank | J96: Shankdeep | K96: 46139 | N96: 46232 | P96: Yes
A97: 96 | B97: The Postal & RMS Employees Co-op Bank Ltd. | C97: SAQ AUDIT | D97: Alphae | G97: Completed | H97: Bank | J97: Ketan | K97: 46140 | N97: 46231 | P97: Yes
A98: 97 | B98: Jalore Nagrik Sahakari Bank Ltd. | C98: IT/IS AUDIT | D98: Vineet | G98: Completed | H98: Bank | J98: Shankdeep | K98: 46140 | N98: 46225 | P98: Yes
A99: 98 | B99: Jalore Nagrik Sahakari Bank Ltd. | C99: SAQ AUDIT | D99: Vineet | G99: Completed | H99: Bank | J99: Shankdeep | K99: 46140 | N99: 46218 | P99: Yes
A100: 99 | B100: Jalore Nagrik Sahakari Bank Ltd. | C100: NEFT-RTGS | D100: Vineet | G100: Completed | H100: Bank | J100: Shankdeep | K100: 46140 | N100: 46231 | P100: Yes
A101: 100 | B101: PATAN CO-OPERATIVE BANK LTD | C101: SAQ AUDIT | D101: Alphae | G101: Completed | H101: Bank | J101: Shankdeep | K101: 46093 | P101: Yes
A102: 101 | B102: THE CENTRAL CO OPERATIVE BANK LTD | C102: IT/IS AUDIT | D102: Deven | G102: Completed | H102: Bank | J102: Akshar | K102: 46142 | P102: Yes
A103: 102 | B103: The Udaipur Central Co-operative Bank Ltd. | C103: IT/IS AUDIT | D103: Deven | G103: Completed | H103: Bank | J103: Shankdeep | K103: 46146 | P103: Yes
A104: 103 | B104: Kota Nagrik Sahkari Bank Ltd. | C104: SAQ AUDIT | D104: Zubeda | G104: Completed | H104: Bank | J104: Shankdeep | K104: 46042 | P104: Yes
A105: 104 | B105: TM Systems | C105: SAR AUDIT (DC & DR) | D105: Dimple | G105: Completed | H105: Bank | J105: Nikhil | K105: 46119 | P105: Yes
A106: 105 | B106: The Gandhinagar Nagrik Co-operative Bank Ltd | C106: Maturity Assessment | D106: Vineet | G106: Not Started | H106: Bank | J106: Shankdeep | K106: 46150 | P106: No
A107: 106 | B107: The Gandhinagar Nagrik Co-operative Bank Ltd | C107: SAR | D107: Vineet | G107: Not Started | H107: Bank | J107: Shankdeep | K107: 46150 | P107: No
A108: 107 | B108: The Gandhinagar Nagrik Co-operative Bank Ltd | C108: IT/IS AUDIT | D108: Vineet | G108: Not Started | H108: Bank | J108: Shankdeep | K108: 46150 | P108: No
A109: 108 | B109: The Gandhinagar Nagrik Co-operative Bank Ltd | C109: SAQ AUDIT | D109: Vineet | G109: Not Started | H109: Bank | J109: Shankdeep | K109: 46150 | P109: No
A110: 109 | B110: The Urban Cooperative Bank Ltd | C110: SAQ AUDIT | D110: Gourav | G110: Completed | H110: Bank | J110: Ketan | K110: 46153 | P110: Yes
A111: 110 | B111: The Saurashtra Co-operative Bank Limited | C111: IT/IS AUDIT/EDp | D111: Gourav | G111: Completed | H111: Bank | J111: Ketan | K111: 46153 | P111: Yes
...
